intelicity/__init__.py
intelicity/ai_object.py
intelicity/bound_box.py
intelicity/containers.py
intelicity/contents.py
intelicity/file_header.py
intelicity/folder_header.py
intelicity/geo_location.py
intelicity/image.py
intelicity/main.py
src/__init__.py
src/ai_object.py
src/bound_box.py
src/containers.py
src/contents.py
src/file_header.py
src/geo_location.py
src/image.py
src/main.py
intelicity-0.0.11.dist-info/LICENSE
intelicity-0.0.11.dist-info/METADATA
intelicity-0.0.11.dist-info/WHEEL
intelicity-0.0.11.dist-info/top_level.txt
intelicity-0.0.11.dist-info/RECORD
